README.md
setup.cfg
setup.py
sfgad/__init__.py
sfgad/algorithms.py
sfgad/analyzer.py
sfgad.egg-info/PKG-INFO
sfgad.egg-info/SOURCES.txt
sfgad.egg-info/dependency_links.txt
sfgad.egg-info/requires.txt
sfgad.egg-info/top_level.txt
sfgad/aggregation/__init__.py
sfgad/aggregation/graph_scan.py
sfgad/evaluation/__init__.py
sfgad/modules/__init__.py
sfgad/modules/features/__init__.py
sfgad/modules/features/external_feature.py
sfgad/modules/features/feature.py
sfgad/modules/features/hotspot_features.py
sfgad/modules/features/incident_triangles.py
sfgad/modules/features/incident_triangles_by_type.py
sfgad/modules/features/two_hop_reach.py
sfgad/modules/features/two_hop_reach_by_type.py
sfgad/modules/features/vertex_activity.py
sfgad/modules/features/vertex_activity_by_type.py
sfgad/modules/features/vertex_degree.py
sfgad/modules/features/vertex_degree_by_type.py
sfgad/modules/features/vertex_degree_difference.py
sfgad/modules/features/vertex_degree_difference_by_type.py
sfgad/modules/features/helper/__init__.py
sfgad/modules/features/helper/hotspot_interpreter.py
sfgad/modules/observation_selection/__init__.py
sfgad/modules/observation_selection/additional_selection.py
sfgad/modules/observation_selection/alternative_selection.py
sfgad/modules/observation_selection/current_age_all_selection.py
sfgad/modules/observation_selection/current_age_similar_selection.py
sfgad/modules/observation_selection/current_all_selection.py
sfgad/modules/observation_selection/current_similar_selection.py
sfgad/modules/observation_selection/fallback_selection.py
sfgad/modules/observation_selection/historic_age_all_selection.py
sfgad/modules/observation_selection/historic_age_similar_selection.py
sfgad/modules/observation_selection/historic_all_selection.py
sfgad/modules/observation_selection/historic_same_selection.py
sfgad/modules/observation_selection/historic_similar_selection.py
sfgad/modules/observation_selection/maximum_alternative_selection.py
sfgad/modules/observation_selection/minimum_alternative_selection.py
sfgad/modules/observation_selection/observation_selection.py
sfgad/modules/observation_selection/helper/__init__.py
