Metadata-Version: 2.1
Name: sfgad
Version: 0.1.1
Summary: A statistical framework for graph anomaly detection
Home-page: https://github.com/sudrich/sf-gad
Maintainer: Simon Sudrich
Maintainer-email: uzcyg@student.kit.edu
License: GPL-3.0
Download-URL: https://api.github.com/repos/sudrich/sf-gad/tarball/master
Platform: UNKNOWN
